<annotation>
	<folder>ningbo_car01_2</folder>
	<filename>23.jpg</filename>
	<path>D:\Desktop\GitHub\ObstacleDetection_Result\data\ningbo_car01_2\23.jpg</path>
	<source>
		<database>Unknown</database>
	</source>
	<size>
		<width>1920</width>
		<height>1080</height>
		<depth>3</depth>
	</size>
	<segmented>0</segmented>
	<object>
		<name>AGmachine</name>
		<pose>Unspecified</pose>
		<truncated>1</truncated>
		<difficult>0</difficult>
		<bndbox>
			<xmin>1</xmin>
			<ymin>441</ymin>
			<xmax>143</xmax>
			<ymax>537</ymax>
		</bndbox>
	</object>
	<object>
		<name>AGmachine</name>
		<pose>Unspecified</pose>
		<truncated>0</truncated>
		<difficult>0</difficult>
		<bndbox>
			<xmin>776</xmin>
			<ymin>480</ymin>
			<xmax>843</xmax>
			<ymax>537</ymax>
		</bndbox>
	</object>
	<object>
		<name>people</name>
		<pose>Unspecified</pose>
		<truncated>0</truncated>
		<difficult>0</difficult>
		<bndbox>
			<xmin>1320</xmin>
			<ymin>512</ymin>
			<xmax>1340</xmax>
			<ymax>541</ymax>
		</bndbox>
	</object>
</annotation>
